nonebot_plugin_chatgpt/__init__.py
nonebot_plugin_chatgpt/chatgpt.py
nonebot_plugin_chatgpt/config.py
nonebot_plugin_chatgpt/data.py
nonebot_plugin_chatgpt/utils.py
nonebot_plugin_chatgpt-0.7.5.dist-info/WHEEL
nonebot_plugin_chatgpt-0.7.5.dist-info/METADATA
nonebot_plugin_chatgpt-0.7.5.dist-info/licenses/LICENSE
nonebot_plugin_chatgpt-0.7.5.dist-info/RECORD
