Metadata-Version: 2.1
Name: nonebot-plugin-chatgpt
Version: 0.7.5
Summary: NoneBot2 plugin for AI chat
License: MIT
Author-email: Akirami <Akiramiaya@outlook.com>
Requires-Python: >=3.8
Requires-Dist: OpenAIAuth>=0.0.3.1
Requires-Dist: nonebot-adapter-onebot>=2.1.5
Requires-Dist: nonebot-plugin-apscheduler>=0.2.0
Requires-Dist: nonebot-plugin-htmlrender>=0.2.0.1
Requires-Dist: nonebot2>=2.0.0rc2
Project-URL: Homepage, https://github.com/A-kirami/nonebot-plugin-chatgpt
Project-URL: Repository, https://github.com/A-kirami/nonebot-plugin-chatgpt
